{
 "custom_fields": [
  {
   "_assign": null,
   "_comments": null,
   "_liked_by": null,
   "_user_tags": null,
   "allow_in_quick_entry": 0,
   "allow_on_submit": 0,
   "bold": 0,
   "collapsible": 0,
   "collapsible_depends_on": null,
   "columns": 0,
   "creation": "2021-07-19 23:22:15.976392",
   "default": null,
   "depends_on": null,
   "description": null,
   "docstatus": 0,
   "dt": "Patient Encounter",
   "fetch_from": "patient.no_identificacion",
   "fetch_if_empty": 0,
   "fieldname": "no_identificacion",
   "fieldtype": "Data",
   "hidden": 0,
   "hide_border": 0,
   "hide_days": 0,
   "hide_seconds": 0,
   "idx": 7,
   "ignore_user_permissions": 0,
   "ignore_xss_filter": 0,
   "in_global_search": 0,
   "in_list_view": 1,
   "in_preview": 0,
   "in_standard_filter": 0,
   "insert_after": "patient_name",
   "label": "No Identificaci\u00f3n",
   "length": 0,
   "mandatory_depends_on": null,
   "modified": "2021-07-19 23:22:15.976392",
   "modified_by": "Administrator",
   "name": "Patient Encounter-no_identificacion",
   "no_copy": 0,
   "non_negative": 0,
   "options": null,
   "owner": "Administrator",
   "parent": null,
   "parentfield": null,
   "parenttype": null,
   "permlevel": 0,
   "precision": "",
   "print_hide": 0,
   "print_hide_if_no_value": 0,
   "print_width": null,
   "read_only": 0,
   "read_only_depends_on": null,
   "report_hide": 0,
   "reqd": 0,
   "search_index": 0,
   "translatable": 1,
   "unique": 0,
   "width": null
  },
  {
   "_assign": null,
   "_comments": null,
   "_liked_by": null,
   "_user_tags": null,
   "allow_in_quick_entry": 0,
   "allow_on_submit": 0,
   "bold": 0,
   "collapsible": 0,
   "collapsible_depends_on": null,
   "columns": 0,
   "creation": "2021-08-23 12:41:31.734667",
   "default": null,
   "depends_on": null,
   "description": null,
   "docstatus": 0,
   "dt": "Patient Encounter",
   "fetch_from": null,
   "fetch_if_empty": 0,
   "fieldname": "2_cabeza",
   "fieldtype": "Check",
   "hidden": 0,
   "hide_border": 0,
   "hide_days": 0,
   "hide_seconds": 0,
   "idx": 22,
   "ignore_user_permissions": 0,
   "ignore_xss_filter": 0,
   "in_global_search": 0,
   "in_list_view": 0,
   "in_preview": 0,
   "in_standard_filter": 0,
   "insert_after": "1_viaobstruida",
   "label": "2 Cabeza",
   "length": 0,
   "mandatory_depends_on": null,
   "modified": "2021-08-23 12:41:31.734667",
   "modified_by": "Administrator",
   "name": "Patient Encounter-2_cabeza",
   "no_copy": 0,
   "non_negative": 0,
   "options": null,
   "owner": "Administrator",
   "parent": null,
   "parentfield": null,
   "parenttype": null,
   "permlevel": 0,
   "precision": "",
   "print_hide": 0,
   "print_hide_if_no_value": 0,
   "print_width": null,
   "read_only": 0,
   "read_only_depends_on": null,
   "report_hide": 0,
   "reqd": 0,
   "search_index": 0,
   "translatable": 0,
   "unique": 0,
   "width": null
  },
  {
   "_assign": null,
   "_comments": null,
   "_liked_by": null,
   "_user_tags": null,
   "allow_in_quick_entry": 0,
   "allow_on_submit": 0,
   "bold": 0,
   "collapsible": 0,
   "collapsible_depends_on": null,
   "columns": 0,
   "creation": "2021-08-23 12:41:32.412709",
   "default": null,
   "depends_on": null,
   "description": null,
   "docstatus": 0,
   "dt": "Patient Encounter",
   "fetch_from": null,
   "fetch_if_empty": 0,
   "fieldname": "3_cuello",
   "fieldtype": "Check",
   "hidden": 0,
   "hide_border": 0,
   "hide_days": 0,
   "hide_seconds": 0,
   "idx": 23,
   "ignore_user_permissions": 0,
   "ignore_xss_filter": 0,
   "in_global_search": 0,
   "in_list_view": 0,
   "in_preview": 0,
   "in_standard_filter": 0,
   "insert_after": "2_cabeza",
   "label": "3 Cuello",
   "length": 0,
   "mandatory_depends_on": null,
   "modified": "2021-08-23 12:41:32.412709",
   "modified_by": "Administrator",
   "name": "Patient Encounter-3_cuello",
   "no_copy": 0,
   "non_negative": 0,
   "options": null,
   "owner": "Administrator",
   "parent": null,
   "parentfield": null,
   "parenttype": null,
   "permlevel": 0,
   "precision": "",
   "print_hide": 0,
   "print_hide_if_no_value": 0,
   "print_width": null,
   "read_only": 0,
   "read_only_depends_on": null,
   "report_hide": 0,
   "reqd": 0,
   "search_index": 0,
   "translatable": 0,
   "unique": 0,
   "width": null
  },
  {
   "_assign": null,
   "_comments": null,
   "_liked_by": null,
   "_user_tags": null,
   "allow_in_quick_entry": 0,
   "allow_on_submit": 0,
   "bold": 0,
   "collapsible": 0,
   "collapsible_depends_on": null,
   "columns": 0,
   "creation": "2021-08-23 12:41:33.205910",
   "default": null,
   "depends_on": null,
   "description": null,
   "docstatus": 0,
   "dt": "Patient Encounter",
   "fetch_from": null,
   "fetch_if_empty": 0,
   "fieldname": "4_torax",
   "fieldtype": "Check",
   "hidden": 0,
   "hide_border": 0,
   "hide_days": 0,
   "hide_seconds": 0,
   "idx": 24,
   "ignore_user_permissions": 0,
   "ignore_xss_filter": 0,
   "in_global_search": 0,
   "in_list_view": 0,
   "in_preview": 0,
   "in_standard_filter": 0,
   "insert_after": "3_cuello",
   "label": "4 Torax",
   "length": 0,
   "mandatory_depends_on": null,
   "modified": "2021-08-23 12:41:33.205910",
   "modified_by": "Administrator",
   "name": "Patient Encounter-4_torax",
   "no_copy": 0,
   "non_negative": 0,
   "options": null,
   "owner": "Administrator",
   "parent": null,
   "parentfield": null,
   "parenttype": null,
   "permlevel": 0,
   "precision": "",
   "print_hide": 0,
   "print_hide_if_no_value": 0,
   "print_width": null,
   "read_only": 0,
   "read_only_depends_on": null,
   "report_hide": 0,
   "reqd": 0,
   "search_index": 0,
   "translatable": 0,
   "unique": 0,
   "width": null
  },
  {
   "_assign": null,
   "_comments": null,
   "_liked_by": null,
   "_user_tags": null,
   "allow_in_quick_entry": 0,
   "allow_on_submit": 0,
   "bold": 0,
   "collapsible": 0,
   "collapsible_depends_on": null,
   "columns": 0,
   "creation": "2021-08-23 12:41:33.956294",
   "default": null,
   "depends_on": null,
   "description": null,
   "docstatus": 0,
   "dt": "Patient Encounter",
   "fetch_from": null,
   "fetch_if_empty": 0,
   "fieldname": "5_abdomen",
   "fieldtype": "Check",
   "hidden": 0,
   "hide_border": 0,
   "hide_days": 0,
   "hide_seconds": 0,
   "idx": 25,
   "ignore_user_permissions": 0,
   "ignore_xss_filter": 0,
   "in_global_search": 0,
   "in_list_view": 0,
   "in_preview": 0,
   "in_standard_filter": 0,
   "insert_after": "4_torax",
   "label": "5 Abdomen",
   "length": 0,
   "mandatory_depends_on": null,
   "modified": "2021-08-23 12:41:33.956294",
   "modified_by": "Administrator",
   "name": "Patient Encounter-5_abdomen",
   "no_copy": 0,
   "non_negative": 0,
   "options": null,
   "owner": "Administrator",
   "parent": null,
   "parentfield": null,
   "parenttype": null,
   "permlevel": 0,
   "precision": "",
   "print_hide": 0,
   "print_hide_if_no_value": 0,
   "print_width": null,
   "read_only": 0,
   "read_only_depends_on": null,
   "report_hide": 0,
   "reqd": 0,
   "search_index": 0,
   "translatable": 0,
   "unique": 0,
   "width": null
  },
  {
   "_assign": null,
   "_comments": null,
   "_liked_by": null,
   "_user_tags": null,
   "allow_in_quick_entry": 0,
   "allow_on_submit": 0,
   "bold": 0,
   "collapsible": 0,
   "collapsible_depends_on": null,
   "columns": 0,
   "creation": "2021-08-23 12:41:34.609079",
   "default": null,
   "depends_on": null,
   "description": null,
   "docstatus": 0,
   "dt": "Patient Encounter",
   "fetch_from": null,
   "fetch_if_empty": 0,
   "fieldname": "6_columna",
   "fieldtype": "Check",
   "hidden": 0,
   "hide_border": 0,
   "hide_days": 0,
   "hide_seconds": 0,
   "idx": 26,
   "ignore_user_permissions": 0,
   "ignore_xss_filter": 0,
   "in_global_search": 0,
   "in_list_view": 0,
   "in_preview": 0,
   "in_standard_filter": 0,
   "insert_after": "5_abdomen",
   "label": "6 Columna",
   "length": 0,
   "mandatory_depends_on": null,
   "modified": "2021-08-23 12:41:34.609079",
   "modified_by": "Administrator",
   "name": "Patient Encounter-6_columna",
   "no_copy": 0,
   "non_negative": 0,
   "options": null,
   "owner": "Administrator",
   "parent": null,
   "parentfield": null,
   "parenttype": null,
   "permlevel": 0,
   "precision": "",
   "print_hide": 0,
   "print_hide_if_no_value": 0,
   "print_width": null,
   "read_only": 0,
   "read_only_depends_on": null,
   "report_hide": 0,
   "reqd": 0,
   "search_index": 0,
   "translatable": 0,
   "unique": 0,
   "width": null
  },
  {
   "_assign": null,
   "_comments": null,
   "_liked_by": null,
   "_user_tags": null,
   "allow_in_quick_entry": 0,
   "allow_on_submit": 0,
   "bold": 0,
   "collapsible": 0,
   "collapsible_depends_on": null,
   "columns": 0,
   "creation": "2021-08-23 12:41:35.276981",
   "default": null,
   "depends_on": null,
   "description": null,
   "docstatus": 0,
   "dt": "Patient Encounter",
   "fetch_from": null,
   "fetch_if_empty": 0,
   "fieldname": "7_pelvis",
   "fieldtype": "Check",
   "hidden": 0,
   "hide_border": 0,
   "hide_days": 0,
   "hide_seconds": 0,
   "idx": 27,
   "ignore_user_permissions": 0,
   "ignore_xss_filter": 0,
   "in_global_search": 0,
   "in_list_view": 0,
   "in_preview": 0,
   "in_standard_filter": 0,
   "insert_after": "6_columna",
   "label": "7 Pelvis",
   "length": 0,
   "mandatory_depends_on": null,
   "modified": "2021-08-23 12:41:35.276981",
   "modified_by": "Administrator",
   "name": "Patient Encounter-7_pelvis",
   "no_copy": 0,
   "non_negative": 0,
   "options": null,
   "owner": "Administrator",
   "parent": null,
   "parentfield": null,
   "parenttype": null,
   "permlevel": 0,
   "precision": "",
   "print_hide": 0,
   "print_hide_if_no_value": 0,
   "print_width": null,
   "read_only": 0,
   "read_only_depends_on": null,
   "report_hide": 0,
   "reqd": 0,
   "search_index": 0,
   "translatable": 0,
   "unique": 0,
   "width": null
  },
  {
   "_assign": null,
   "_comments": null,
   "_liked_by": null,
   "_user_tags": null,
   "allow_in_quick_entry": 0,
   "allow_on_submit": 0,
   "bold": 0,
   "collapsible": 0,
   "collapsible_depends_on": null,
   "columns": 0,
   "creation": "2021-08-23 12:41:35.958648",
   "default": null,
   "depends_on": null,
   "description": null,
   "docstatus": 0,
   "dt": "Patient Encounter",
   "fetch_from": null,
   "fetch_if_empty": 0,
   "fieldname": "8_extremidades",
   "fieldtype": "Check",
   "hidden": 0,
   "hide_border": 0,
   "hide_days": 0,
   "hide_seconds": 0,
   "idx": 28,
   "ignore_user_permissions": 0,
   "ignore_xss_filter": 0,
   "in_global_search": 0,
   "in_list_view": 0,
   "in_preview": 0,
   "in_standard_filter": 0,
   "insert_after": "7_pelvis",
   "label": "8 Extremidades",
   "length": 0,
   "mandatory_depends_on": null,
   "modified": "2021-08-23 12:41:35.958648",
   "modified_by": "Administrator",
   "name": "Patient Encounter-8_extremidades",
   "no_copy": 0,
   "non_negative": 0,
   "options": null,
   "owner": "Administrator",
   "parent": null,
   "parentfield": null,
   "parenttype": null,
   "permlevel": 0,
   "precision": "",
   "print_hide": 0,
   "print_hide_if_no_value": 0,
   "print_width": null,
   "read_only": 0,
   "read_only_depends_on": null,
   "report_hide": 0,
   "reqd": 0,
   "search_index": 0,
   "translatable": 0,
   "unique": 0,
   "width": null
  },
  {
   "_assign": null,
   "_comments": null,
   "_liked_by": null,
   "_user_tags": null,
   "allow_in_quick_entry": 0,
   "allow_on_submit": 0,
   "bold": 0,
   "collapsible": 0,
   "collapsible_depends_on": null,
   "columns": 0,
   "creation": "2021-08-23 12:41:36.637550",
   "default": null,
   "depends_on": null,
   "description": null,
   "docstatus": 0,
   "dt": "Patient Encounter",
   "fetch_from": null,
   "fetch_if_empty": 0,
   "fieldname": "column_break_28",
   "fieldtype": "Column Break",
   "hidden": 0,
   "hide_border": 0,
   "hide_days": 0,
   "hide_seconds": 0,
   "idx": 29,
   "ignore_user_permissions": 0,
   "ignore_xss_filter": 0,
   "in_global_search": 0,
   "in_list_view": 0,
   "in_preview": 0,
   "in_standard_filter": 0,
   "insert_after": "8_extremidades",
   "label": null,
   "length": 0,
   "mandatory_depends_on": null,
   "modified": "2021-08-23 12:41:36.637550",
   "modified_by": "Administrator",
   "name": "Patient Encounter-column_break_28",
   "no_copy": 0,
   "non_negative": 0,
   "options": null,
   "owner": "Administrator",
   "parent": null,
   "parentfield": null,
   "parenttype": null,
   "permlevel": 0,
   "precision": "",
   "print_hide": 0,
   "print_hide_if_no_value": 0,
   "print_width": null,
   "read_only": 0,
   "read_only_depends_on": null,
   "report_hide": 0,
   "reqd": 0,
   "search_index": 0,
   "translatable": 0,
   "unique": 0,
   "width": null
  },
  {
   "_assign": null,
   "_comments": null,
   "_liked_by": null,
   "_user_tags": null,
   "allow_in_quick_entry": 0,
   "allow_on_submit": 0,
   "bold": 0,
   "collapsible": 0,
   "collapsible_depends_on": null,
   "columns": 0,
   "creation": "2022-01-06 00:04:18.279023",
   "default": null,
   "depends_on": null,
   "description": null,
   "docstatus": 0,
   "dt": "Patient Encounter",
   "fetch_from": null,
   "fetch_if_empty": 0,
   "fieldname": "receta",
   "fieldtype": "Section Break",
   "hidden": 0,
   "hide_border": 0,
   "hide_days": 0,
   "hide_seconds": 0,
   "idx": 40,
   "ignore_user_permissions": 0,
   "ignore_xss_filter": 0,
   "in_global_search": 0,
   "in_list_view": 0,
   "in_preview": 0,
   "in_standard_filter": 0,
   "insert_after": "drug_prescription",
   "label": "RECETA",
   "length": 0,
   "mandatory_depends_on": null,
   "modified": "2022-01-06 00:04:18.279023",
   "modified_by": "Administrator",
   "name": "Patient Encounter-receta",
   "no_copy": 0,
   "non_negative": 0,
   "options": null,
   "owner": "Administrator",
   "parent": null,
   "parentfield": null,
   "parenttype": null,
   "permlevel": 0,
   "precision": "",
   "print_hide": 0,
   "print_hide_if_no_value": 0,
   "print_width": null,
   "read_only": 0,
   "read_only_depends_on": null,
   "report_hide": 0,
   "reqd": 0,
   "search_index": 0,
   "translatable": 0,
   "unique": 0,
   "width": null
  },
  {
   "_assign": null,
   "_comments": null,
   "_liked_by": null,
   "_user_tags": null,
   "allow_in_quick_entry": 0,
   "allow_on_submit": 0,
   "bold": 0,
   "collapsible": 0,
   "collapsible_depends_on": null,
   "columns": 0,
   "creation": "2022-01-06 00:04:19.894413",
   "default": null,
   "depends_on": null,
   "description": null,
   "docstatus": 0,
   "dt": "Patient Encounter",
   "fetch_from": null,
   "fetch_if_empty": 0,
   "fieldname": "rp",
   "fieldtype": "Text",
   "hidden": 0,
   "hide_border": 0,
   "hide_days": 0,
   "hide_seconds": 0,
   "idx": 42,
   "ignore_user_permissions": 0,
   "ignore_xss_filter": 0,
   "in_global_search": 0,
   "in_list_view": 0,
   "in_preview": 0,
   "in_standard_filter": 0,
   "insert_after": "nreceta_siguiente",
   "label": "RP",
   "length": 0,
   "mandatory_depends_on": null,
   "modified": "2022-01-06 00:04:19.894413",
   "modified_by": "Administrator",
   "name": "Patient Encounter-rp",
   "no_copy": 0,
   "non_negative": 0,
   "options": null,
   "owner": "Administrator",
   "parent": null,
   "parentfield": null,
   "parenttype": null,
   "permlevel": 0,
   "precision": "",
   "print_hide": 0,
   "print_hide_if_no_value": 0,
   "print_width": null,
   "read_only": 0,
   "read_only_depends_on": null,
   "report_hide": 0,
   "reqd": 0,
   "search_index": 0,
   "translatable": 0,
   "unique": 0,
   "width": null
  },
  {
   "_assign": null,
   "_comments": null,
   "_liked_by": null,
   "_user_tags": null,
   "allow_in_quick_entry": 0,
   "allow_on_submit": 0,
   "bold": 0,
   "collapsible": 0,
   "collapsible_depends_on": null,
   "columns": 0,
   "creation": "2022-01-06 00:04:21.343614",
   "default": null,
   "depends_on": null,
   "description": null,
   "docstatus": 0,
   "dt": "Patient Encounter",
   "fetch_from": null,
   "fetch_if_empty": 0,
   "fieldname": "column_break_41",
   "fieldtype": "Column Break",
   "hidden": 0,
   "hide_border": 0,
   "hide_days": 0,
   "hide_seconds": 0,
   "idx": 43,
   "ignore_user_permissions": 0,
   "ignore_xss_filter": 0,
   "in_global_search": 0,
   "in_list_view": 0,
   "in_preview": 0,
   "in_standard_filter": 0,
   "insert_after": "rp",
   "label": null,
   "length": 0,
   "mandatory_depends_on": null,
   "modified": "2022-01-06 00:04:21.343614",
   "modified_by": "Administrator",
   "name": "Patient Encounter-column_break_41",
   "no_copy": 0,
   "non_negative": 0,
   "options": null,
   "owner": "Administrator",
   "parent": null,
   "parentfield": null,
   "parenttype": null,
   "permlevel": 0,
   "precision": "",
   "print_hide": 0,
   "print_hide_if_no_value": 0,
   "print_width": null,
   "read_only": 0,
   "read_only_depends_on": null,
   "report_hide": 0,
   "reqd": 0,
   "search_index": 0,
   "translatable": 0,
   "unique": 0,
   "width": null
  },
  {
   "_assign": null,
   "_comments": null,
   "_liked_by": null,
   "_user_tags": null,
   "allow_in_quick_entry": 0,
   "allow_on_submit": 0,
   "bold": 0,
   "collapsible": 0,
   "collapsible_depends_on": null,
   "columns": 0,
   "creation": "2022-01-06 00:04:22.767439",
   "default": null,
   "depends_on": null,
   "description": null,
   "docstatus": 0,
   "dt": "Patient Encounter",
   "fetch_from": null,
   "fetch_if_empty": 0,
   "fieldname": "indicaciones",
   "fieldtype": "Text",
   "hidden": 0,
   "hide_border": 0,
   "hide_days": 0,
   "hide_seconds": 0,
   "idx": 44,
   "ignore_user_permissions": 0,
   "ignore_xss_filter": 0,
   "in_global_search": 0,
   "in_list_view": 0,
   "in_preview": 0,
   "in_standard_filter": 0,
   "insert_after": "column_break_41",
   "label": "Indicaciones",
   "length": 0,
   "mandatory_depends_on": null,
   "modified": "2022-01-06 00:04:22.767439",
   "modified_by": "Administrator",
   "name": "Patient Encounter-indicaciones",
   "no_copy": 0,
   "non_negative": 0,
   "options": null,
   "owner": "Administrator",
   "parent": null,
   "parentfield": null,
   "parenttype": null,
   "permlevel": 0,
   "precision": "",
   "print_hide": 0,
   "print_hide_if_no_value": 0,
   "print_width": null,
   "read_only": 0,
   "read_only_depends_on": null,
   "report_hide": 0,
   "reqd": 0,
   "search_index": 0,
   "translatable": 0,
   "unique": 0,
   "width": null
  },
  {
   "_assign": null,
   "_comments": null,
   "_liked_by": null,
   "_user_tags": null,
   "allow_in_quick_entry": 0,
   "allow_on_submit": 0,
   "bold": 0,
   "collapsible": 0,
   "collapsible_depends_on": null,
   "columns": 0,
   "creation": "2022-01-16 05:19:46.926879",
   "default": null,
   "depends_on": null,
   "description": null,
   "docstatus": 0,
   "dt": "Patient Encounter",
   "fetch_from": null,
   "fetch_if_empty": 0,
   "fieldname": "nreceta_siguiente",
   "fieldtype": "Int",
   "hidden": 0,
   "hide_border": 0,
   "hide_days": 0,
   "hide_seconds": 0,
   "idx": 41,
   "ignore_user_permissions": 0,
   "ignore_xss_filter": 0,
   "in_global_search": 0,
   "in_list_view": 0,
   "in_preview": 0,
   "in_standard_filter": 0,
   "insert_after": "receta",
   "label": "nreceta_siguiente",
   "length": 0,
   "mandatory_depends_on": null,
   "modified": "2022-01-16 05:19:46.926879",
   "modified_by": "Administrator",
   "name": "Patient Encounter-nreceta_siguiente",
   "no_copy": 0,
   "non_negative": 0,
   "options": null,
   "owner": "Administrator",
   "parent": null,
   "parentfield": null,
   "parenttype": null,
   "permlevel": 0,
   "precision": "",
   "print_hide": 0,
   "print_hide_if_no_value": 0,
   "print_width": null,
   "read_only": 0,
   "read_only_depends_on": null,
   "report_hide": 0,
   "reqd": 0,
   "search_index": 0,
   "translatable": 0,
   "unique": 0,
   "width": null
  },
  {
   "_assign": null,
   "_comments": null,
   "_liked_by": null,
   "_user_tags": null,
   "allow_in_quick_entry": 0,
   "allow_on_submit": 0,
   "bold": 0,
   "collapsible": 0,
   "collapsible_depends_on": null,
   "columns": 0,
   "creation": "2022-01-16 05:20:40.771100",
   "default": null,
   "depends_on": null,
   "description": null,
   "docstatus": 0,
   "dt": "Patient Encounter",
   "fetch_from": null,
   "fetch_if_empty": 0,
   "fieldname": "1_viaobstruida",
   "fieldtype": "Data",
   "hidden": 0,
   "hide_border": 0,
   "hide_days": 0,
   "hide_seconds": 0,
   "idx": 21,
   "ignore_user_permissions": 0,
   "ignore_xss_filter": 0,
   "in_global_search": 0,
   "in_list_view": 0,
   "in_preview": 0,
   "in_standard_filter": 0,
   "insert_after": "sb_symptoms",
   "label": "1_viaobstruida",
   "length": 0,
   "mandatory_depends_on": null,
   "modified": "2022-01-16 05:20:40.771100",
   "modified_by": "Administrator",
   "name": "Patient Encounter-1_viaobstruida",
   "no_copy": 0,
   "non_negative": 0,
   "options": null,
   "owner": "Administrator",
   "parent": null,
   "parentfield": null,
   "parenttype": null,
   "permlevel": 0,
   "precision": "",
   "print_hide": 0,
   "print_hide_if_no_value": 0,
   "print_width": null,
   "read_only": 0,
   "read_only_depends_on": null,
   "report_hide": 0,
   "reqd": 0,
   "search_index": 0,
   "translatable": 1,
   "unique": 0,
   "width": null
  }
 ],
 "custom_perms": [],
 "doctype": "Patient Encounter",
 "property_setters": [
  {
   "_assign": null,
   "_comments": null,
   "_liked_by": null,
   "_user_tags": null,
   "creation": "2022-01-07 09:14:55.499942",
   "default_value": null,
   "doc_type": "Patient Encounter",
   "docstatus": 0,
   "doctype_or_field": "DocField",
   "field_name": "sb_drug_prescription",
   "idx": 0,
   "modified": "2022-01-07 09:14:55.499942",
   "modified_by": "Administrator",
   "name": "Patient Encounter-sb_drug_prescription-collapsible",
   "owner": "Administrator",
   "parent": null,
   "parentfield": null,
   "parenttype": null,
   "property": "collapsible",
   "property_type": "Check",
   "row_name": null,
   "value": "1"
  },
  {
   "_assign": null,
   "_comments": null,
   "_liked_by": null,
   "_user_tags": null,
   "creation": "2022-01-07 09:14:55.069482",
   "default_value": null,
   "doc_type": "Patient Encounter",
   "docstatus": 0,
   "doctype_or_field": "DocField",
   "field_name": "codification",
   "idx": 0,
   "modified": "2022-01-07 09:14:55.069482",
   "modified_by": "Administrator",
   "name": "Patient Encounter-codification-collapsible",
   "owner": "Administrator",
   "parent": null,
   "parentfield": null,
   "parenttype": null,
   "property": "collapsible",
   "property_type": "Check",
   "row_name": null,
   "value": "0"
  },
  {
   "_assign": null,
   "_comments": null,
   "_liked_by": null,
   "_user_tags": null,
   "creation": "2021-07-22 14:14:52.525722",
   "default_value": null,
   "doc_type": "Patient Encounter",
   "docstatus": 0,
   "doctype_or_field": "DocField",
   "field_name": "sb_test_prescription",
   "idx": 0,
   "modified": "2021-07-22 14:14:52.525722",
   "modified_by": "Administrator",
   "name": "Patient Encounter-sb_test_prescription-label",
   "owner": "Administrator",
   "parent": null,
   "parentfield": null,
   "parenttype": null,
   "property": "label",
   "property_type": "Data",
   "row_name": null,
   "value": "Pruebas de Laboratorio / Im\u00e1genes"
  }
 ],
 "sync_on_migrate": 1
}